[
  {
    "title": "Indian Girl Teasing",
    "video": "https://files.catbox.moe/vuxja3.mp4",
    "thumbnail": "https://files.catbox.moe/w07sfd.jpg",
    "tags": [
      "nude",
      "boobs",
      "hooker"
    ],
    "category": "Indian",
    "views": "3.4k"
  },
  {
    "title": "Indian Girl Reveals",
    "video": "https://files.catbox.moe/pzj4ht.mp4",
    "thumbnail": "https://files.catbox.moe/d9tkj8.jpg",
    "tags": [
      "nude",
      "boobs",
      "pussy"
    ],
    "category": "Indian",
    "views": "4.1k"
  },
  {
    "title": "Indian Girl Stripping",
    "video": "https://files.catbox.moe/0bdccn.mp4",
    "thumbnail": "https://files.catbox.moe/v7yutm.jpg",
    "tags": [
      "nude",
      "boobs",
      "pussy",
      "ass"
    ],
    "category": "Indian",
    "views": "2.9k"
  },
  {
    "title": "Hot Indian Strip",
    "video": "https://files.catbox.moe/1rly39.mp4",
    "thumbnail": "https://files.catbox.moe/c169qa.jpg",
    "tags": [
      "boobs",
      "pussy",
      "ass"
    ],
    "category": "Indian",
    "views": "3.7k"
  },
  {
    "title": "Sexy Indian Girl",
    "video": "https://files.catbox.moe/7ysqg9.mp4",
    "thumbnail": "https://files.catbox.moe/jw1yj9.jpg",
    "tags": [
      "pussy",
      "ass"
    ],
    "category": "Indian",
    "views": "4.3k"
  },
  {
    "title": "Nude Indian Girl",
    "video": "https://files.catbox.moe/aalfkm.mp4",
    "thumbnail": "https://files.catbox.moe/6mha7w.jpg",
    "tags": [
      "pussy",
      "ass",
      "nudes"
    ],
    "category": "Indian",
    "views": "2.1k"
  },
  {
    "title": "Foreign Girl Strip",
    "video": "https://files.catbox.moe/gvy5p7.mp4",
    "thumbnail": "https://files.catbox.moe/bnuu8s.jpg",
    "tags": [
      "ass",
      "nudes"
    ],
    "category": "Foreign",
    "views": "1.9k"
  }
]